str2time/__init__.py
str2time-1.0.2.dist-info/METADATA
str2time-1.0.2.dist-info/WHEEL
str2time-1.0.2.dist-info/top_level.txt
str2time-1.0.2.dist-info/RECORD
